Workbook
Name DocId: "HA"

Sheet 自动回填说明
A1: 自动回填说明（template-first 真回填 · 人工门2 changes 回修第2轮）
A2: 公司：中国南玻集团股份有限公司
A3: 材料范围：仅销售合同 + 出库单。发票/记账凭证/明细账不在范围，相关列留空（灰底）并标注原因。
A4: 每个样本 = 一个【人工已确认】的材料关联组（合同↔出库），按合同锚定（从合同到明细账）。
A5: ① 合同货物名称(E)/规格(F)/数量(G) 取自合同证据 fields_json（多货物按行项目分条列示，G为合计）；
A6: ② 单价(H) 保留模板公式 =金额(I)/数量(G)，由本行 G/I 自动算出数值；
A7: ③ 物流记录(出库) 按出库日期逐行展开：一个日期一行，编号(Y)汇总该日期全部出库单号，数量(Z)/金额(AA)为该日期合计；合同侧列(序号/B–J)按样本纵向合并。
A8: 黄底 = 关键字段缺失/合同扫描件OCR读不出，需人工补录；灰底 = 范围外；红底 = 该样本结论非“通过测试”，需优先复核。
A9: 出库数量/金额为该客户全期出库台账合计，是否对应本合同批次需人工确认（详见各行备注与异常点清单）。
A10: “从明细账到合同”sheet 需要明细账/记账凭证作为起点，本次范围不含，故未自动生成数据行。
A11: 请配合『异常点清单_<公司>.md』逐条确认后再在终审门处理。

Sheet 主营业务收入细节测试（从合同到明细账）
A1: 主营业务收入细节测试记录表（从合同到明细账） | AN1: =HYPERLINK("#目录!A1","返回目录")
A2: =[1]目录!$A$2&[1]目录!$C$2 | K2: =[1]目录!$A$4&[1]目录!$C$4&" "&[1]目录!$A$5&[1]目录!$C$5 | AM2: ="索引号："&[1]目录!$D$52
A3: =[1]目录!$D$3&[1]目录!$F$3 | K3: =[1]目录!$D$4&[1]目录!$F$4&" "&[1]目录!$D$5&[1]目录!$F$5
A4: 序号 | B4: 销售合同、请购单内容 | Q4: 销售发票 | X4: 物流记录或客户验收单 | AE4: 其他支付性文件或说明 | AF4: 会计凭证 | AM4: 备注
B5: 销售合同或销售订单编号 | C5: 签约日期 | D5: 订购单位名称 | E5: 货物名称 | F5: 规格 | G5: 数量 | H5: 单价 | I5: 金额 | J5: 约定交货时间 | K5: 常规核对 | M5: 追加核对 | Q5: 日期 | R5: 编号 | S5: 数量 | T5: 金额 | U5: 核对 | X5: 日期 | Y5: 编号 | Z5: 数量 | AA5: 金额(如适用) | AB5: 核对 | AF5: 日期 | AG5: 编号 | AH5: 金额 | AI5: 核对
K6: (1) | L6: (2) | M6: (3) | N6: (4) | O6: (5) | P6: (6) | U6: (7) | V6: (8) | W6: (9) | AB6: (10) | AC6: (11) | AD6: (12) | AI6: (13) | AJ6: (14) | AK6: (15) | AL6: (16)
A7: 1 | B7: 4500066334 | C7: 2022-04-07 | D7: 盐城正泰新能源科技有限公司 | E7: ①正面镀膜钢化玻璃_182双玻 2251*1128*2.0mm（35700PC） ②背面网格钢化玻璃_182双玻 2251*1128*2.0mm（35700PC） | F7: ①2251*1128*2.0mm ②2251*1128*2.0mm | G7: 71400 | H7: =I7/G7 | I7: 4122446.8 | J7: 2022-04-30 | K7: 待人工核对 | L7: 待人工核对 | M7: 待人工核对 | N7: 待人工核对 | O7: 待人工核对 | P7: 待人工核对 | X7: 2022-04-29 | Y7: XCD2204290034、XCD2204290037、XCD2204290038、XCD2204290042、XCD2204290043、XCD2204290045、XCD2204290046、XCD2204290057 | Z7: 51798.211 | AA7: 1064125 | AB7: 待人工核对 | AC7: 待人工核对 | AD7: 待人工核对 | AE7: 系统结论：通过测试；合同为多货物采购订单(PO)，货物名称/规格/数量已按行项目分条列示；G列数量=各行项目合计，H列单价=金额/数量(含税加权均价)；合同数量计量单位为「PC」，出库台账计量单位为「平方米」，口径不同，已分列不混填；物流记录(出库)已按出库日期逐行展开：一个日期一行，编号列汇总该日期全部出库单号，数量/金额为该日期合计；出库数量/金额为该客户全期出库台账合计，与单一PO金额口径不同，是否对应本合同批次需人工确认；发票/记账凭证/明细账不在本次材料范围（相应列留空）；勾稽：合同金额(4122446.79) 与出库金额合计(19828766.61) 不一致（口径不同，需人工判断是否合理）
X8: 2022-04-30 | Y8: XCD2205020001、XCD2205020010、XCD2205020011、XCD2205020012、XCD2205020014、XCD2205020019、XCD2205030005、XCD2205030006、XCD2205030007、XCD2205030008、XCD2205030009、XCD2205030010、XCD2205030011、XCD2205030012、XCD2205030013、XCD2205030014、XCD2205030015、XCD2205030016、XCD2205030017、XCD2205030018 | Z8: 129495.53 | AA8: 2474613.7
X9: 2022-05-31 | Y9: CKT2206020005、CKT2206020006、CKT2206020007、CKT2206020008、CKT2206020009、CKT2206020010、CKT2206020011、CKT2206020012、CKT2206020013、CKT2206020014、CKT2206020015、CKT2206020016、CKT2206020017、CKT2206020018、CKT2206020019、CKT2206020020 | AA9: -1.1
X10: 2022-06-28 | Y10: XCD2206280004、XCD2206280031、XCD2206280034、XCD2206280036、XCD2206280037、XCD2206280039、XCD2206280041、XCD2206280048、XCD2206280050、XCD2206280051、XCD2206280052、XCD2206280053、XCD2206280057、XCD2206280059、XCD2206280060 | Z10: 90764.741 | AA10: 1718811
X11: 2022-06-30 | Y11: CKT2207020009、XCD2206300020、XCD2206300021、XCD2206300022、XCD2206300023、XCD2206300024、XCD2206300025、XCD2206300026、XCD2206300027、XCD2206300028、XCD2206300029、XCD2206300030、XCD2206300031、XCD2206300032、XCD2206300033、XCD2206300034 | Z11: 90764.741 | AA11: 1718810.4
X12: 2022-07-28 | Y12: XCD2207280001 | Z12: 512.5632 | AA12: 10451.27
X13: 2022-07-29 | Y13: XCD2207290022 | Z13: 512.5632 | AA13: 10451.27
X14: 2022-09-30 | Y14: XCD2209300021、XCD2209300027、XCD2209300028、XCD2209300029、XCD2209300030、XCD2209300031、XCD2209300032、XCD2209300033、XCD2209300038、XCD2209300039、XCD2209300040、XCD2209300041、XCD2209300044、XCD2209300045、XCD2209300053、XCD2209300054、XCD2209300055、XCD2209300056、XCD2209300057、XCD2209300058、XCD2209300059、XCD2209300060、XCD2209300061、XCD2209300062、XCD2209300063、XCD2209300083、XCD2209300084、XCD2209300085、XCD2209300091、XCD2209300092、XCD2209300093、XCD2209300095、XCD2209300096、XCD2210010028、XCD2210010029、XCD2210010030、XCD2210010031、XCD2210010032、XCD2210010033、XCD2210010034、XCD2210010035、XCD2210010036、XCD2210010037、XCD2210010038、XCD2210010039、XCD2210010040、XCD2210010041、XCD2210010042、XCD2210010043、XCD2210010044、XCD2210010045、XCD2210010046、XCD2210010047、XCD2210010048、XCD2210010049、XCD2210010050、XCD2210010051、XCD2210010052、XCD2210010053、XCD2210010054、XCD2210010055、XCD2210010056、XCD2210010057、XCD2210010058、XCD2210010059、XCD2210010060 | Z14: 430553.09 | AA14: 7423085.6
X15: 2022-10-31 | Y15: XCD2211010009、XCD2211010010、XCD2211010011、XCD2211010012、XCD2211010013、XCD2211010014、XCD2211010015、XCD2211010016、XCD2211010017、XCD2211010018、XCD2211010019、XCD2211010020、XCD2211010021、XCD2211010022、XCD2211010023、XCD2211010024、XCD2211010025、XCD2211010026、XCD2211010027、XCD2211010028、XCD2211010029、XCD2211010030、XCD2211010031、XCD2211010032、XCD2211010268、XCD2211010269、XCD2211010270、XCD2211010271、XCD2211010272、XCD2211010273、XCD2211010274、XCD2211010275、XCD2211010276、XCD2211010277、XCD2211010278、XCD2211010279、XCD2211010280、XCD2211010281、XCD2211010282、XCD2211010283、XCD2211010284、XCD2211010285、XCD2211010286、XCD2211010287、XCD2211010288、XCD2211010289、XCD2211010290、XCD2211010291 | Z15: 313688.68 | AA15: 5408419.4
A16: 2 | B16: JSLJ·ZGNB20221010 | C16: 2022-10-10 | D16: 江苏宇辉光伏科技有限公司 | E16: 单玻玻璃 | F16: 超白压花普通钢化镀膜-2272×1128×3.2mm | G16: 5900 | H16: =I16/G16 | I16: 393117 | J16: 2022年10月17日开始每天两车 | K16: 待人工核对 | L16: 待人工核对 | M16: 待人工核对 | N16: 待人工核对 | O16: 待人工核对 | P16: 待人工核对 | X16: 2022-07-29 | Y16: XCD2207290003、XCD2207290004、XCD2207290005、XCD2207290006、XCD2207290007、XCD2207290008、XCD2207290009、XCD2207290010、XCD2207290011、XCD2207290012、XCD2207290013、XCD2207290014、XCD2207290015、XCD2207290025、XCD2207290026、XCD2207290027、XCD2207290028、XCD2207290029、XCD2207290030、XCD2207290031、XCD2207290032、XCD2207290033、XCD2207290034、XCD2207290035、XCD2207290036、XCD2207290037 | Z16: 106660.07 | AA16: 2518310.1 | AB16: 待人工核对 | AC16: 待人工核对 | AD16: 待人工核对 | AE16: 系统结论：需人工复核；合同数量计量单位为「片」，出库台账计量单位为「平方米」，口径不同，已分列不混填；物流记录(出库)已按出库日期逐行展开：一个日期一行，编号列汇总该日期全部出库单号，数量/金额为该日期合计；出库数量/金额为该客户全期出库台账合计，与单一PO金额口径不同，是否对应本合同批次需人工确认；发票/记账凭证/明细账不在本次材料范围（相应列留空）；勾稽：合同金额(393117.0) 与出库金额合计(12405000.76) 不一致（口径不同，需人工判断是否合理）；签订日期(2022-10-10)晚于出库日期(2022-07-29)
X17: 2022-07-31 | Y17: CKT2208010012、XCD2208010002、XCD2208010003、XCD2208010004、XCD2208010005、XCD2208010006、XCD2208010007、XCD2208010008、XCD2208010009、XCD2208010010、XCD2208010011、XCD2208010012、XCD2208010013 | Z17: 49227.725 | AA17: 1162297.1
X18: 2022-08-16 | Y18: XCD2208160001、XCD2208160002、XCD2208160003、XCD2208160004、XCD2208160005、XCD2208160006、XCD2208160007、XCD2208160008、XCD2208160009、XCD2208160010、XCD2208160011、XCD2208160012、XCD2208160013、XCD2208160014、XCD2208160015、XCD2208160016、XCD2208160017、XCD2208160018、XCD2208160019、XCD2208160020、XCD2208160021、XCD2208160022、XCD2208160023、XCD2208160025 | Z18: 96917.083 | AA18: 2255964.5
X19: 2022-08-31 | Y19: XCD2208310027、XCD2208310028、XCD2208310029、XCD2208310030、XCD2208310031、XCD2208310032、XCD2208310033、XCD2208310034、XCD2208310035、XCD2208310036、XCD2208310037、XCD2208310038、XCD2208310039、XCD2208310040、XCD2208310041、XCD2208310042、XCD2208310043、XCD2208310044、XCD2208310045、XCD2208310046、XCD2208310047、XCD2208310048、XCD2208310049、XCD2208310050 | Z19: 96917.083 | AA19: 2255964.5
X20: 2022-09-30 | Y20: XCD2209300014、XCD2209300015、XCD2209300019、XCD2209300024、XCD2209300036、XCD2209300098、XCD2209300099、XCD2209300100、XCD2209300108、XCD2210010006、XCD2210010061、XCD2210010062、XCD2210010063、XCD2210010064、XCD2210010065、XCD2210010066、XCD2210010067、XCD2210010068、XCD2210010069、XCD2210010070 | Z20: 73830.082 | AA20: 1646665
X21: 2022-10-31 | Y21: CKT2211010013、CKT2211010015、XCD2211010001、XCD2211010002、XCD2211010003、XCD2211010004、XCD2211010052、XCD2211010053、XCD2211010054、XCD2211010055、XCD2211010056、XCD2211010057、XCD2211010058、XCD2211010059、XCD2211010060、XCD2211010061、XCD2211010062、XCD2211010063、XCD2211010064、XCD2211010065、XCD2211010066、XCD2211010156、XCD2211010160、XCD2211010161、XCD2211010162、XCD2211010163、XCD2211010169、XCD2211010221、XCD2211010222、XCD2211010233、XCD2211010234、XCD2211010235 | Z21: 116015.25 | AA21: 2565799.6
A22: 3 | B22: YDQZ202200200 | C22: 2022-10-09 | D22: 一道新能源科技（衢州）有限公司 | E22: 玻璃_镀膜钢化 | F22: 超白压花,2272*1128*3.2 | G22: 12800 | H22: =I22/G22 | I22: 836480 | J22: 2022-10-20 | K22: 待人工核对 | L22: 待人工核对 | M22: 待人工核对 | N22: 待人工核对 | O22: 待人工核对 | P22: 待人工核对 | X22: 2022-08-30 | Y22: XCD2208300001、XCD2208300002、XCD2208300003、XCD2208300004、XCD2208300005、XCD2208300006、XCD2208300008、XCD2208300009、XCD2208300010、XCD2208300011、XCD2208300012、XCD2208300013、XCD2208300014、XCD2208300015、XCD2208300016、XCD2208300017、XCD2208300018、XCD2208300019、XCD2208300020、XCD2208300021 | Z22: 74716.013 | AA22: 1730461.2 | AB22: 待人工核对 | AC22: 待人工核对 | AD22: 待人工核对 | AE22: 系统结论：需人工复核；合同数量计量单位为「块」，出库台账计量单位为「平方米」，口径不同，已分列不混填；物流记录(出库)已按出库日期逐行展开：一个日期一行，编号列汇总该日期全部出库单号，数量/金额为该日期合计；出库数量/金额为该客户全期出库台账合计，与单一PO金额口径不同，是否对应本合同批次需人工确认；发票/记账凭证/明细账不在本次材料范围（相应列留空）；勾稽：合同金额(836480.0) 与出库金额合计(18302295.87) 不一致（口径不同，需人工判断是否合理）；签订日期(2022-10-09)晚于出库日期(2022-08-30)
X23: 2022-08-31 | Y23: XCD2208310005、XCD2208310006、XCD2208310007、XCD2208310008、XCD2208310009、XCD2208310010、XCD2208310011、XCD2208310012、XCD2208310013、XCD2208310014、XCD2208310015、XCD2208310016、XCD2208310017、XCD2208310018、XCD2208310019、XCD2208310020、XCD2208310021、XCD2208310022、XCD2208310023、XCD2208310024 | Z23: 74716.013 | AA23: 1730461.2
X24: 2022-09-30 | Y24: CKT2210020002、XCD2209300002、XCD2209300003、XCD2209300004、XCD2209300005、XCD2209300006、XCD2209300007、XCD2209300008、XCD2209300009、XCD2209300010、XCD2209300011、XCD2209300016、XCD2209300017、XCD2209300018、XCD2209300020、XCD2209300023、XCD2209300035、XCD2209300043、XCD2209300046、XCD2209300047、XCD2209300048、XCD2209300109、XCD2210010003、XCD2210010004、XCD2210010005、XCD2210010095、XCD2210010096、XCD2210010097、XCD2210010098、XCD2210010099、XCD2210010100、XCD2210010101、XCD2210010102、XCD2210010103、XCD2210010104、XCD2210010105、XCD2210010106、XCD2210010107、XCD2210010108、XCD2210010109、XCD2210010110、XCD2210010111、XCD2210010112、XCD2210010113、XCD2210010114、XCD2210010115、XCD2210010116、XCD2210010117、XCD2210010118 | Z24: 187560.42 | AA24: 4182395.2
X25: 2022-10-31 | Y25: CKT2211010001、CKT2211010002、CKT2211010014、XCD2211010005、XCD2211010008、XCD2211010033、XCD2211010034、XCD2211010035、XCD2211010036、XCD2211010037、XCD2211010038、XCD2211010041、XCD2211010125、XCD2211010126、XCD2211010127、XCD2211010128、XCD2211010129、XCD2211010130、XCD2211010131、XCD2211010132、XCD2211010133、XCD2211010134、XCD2211010135、XCD2211010136、XCD2211010137、XCD2211010138、XCD2211010139、XCD2211010140、XCD2211010141、XCD2211010142、XCD2211010143、XCD2211010144、XCD2211010145、XCD2211010146、XCD2211010147、XCD2211010148、XCD2211010149、XCD2211010150、XCD2211010155、XCD2211010157、XCD2211010158、XCD2211010159、XCD2211010164、XCD2211010165、XCD2211010166、XCD2211010167、XCD2211010170、XCD2211010172、XCD2211010174、XCD2211010175、XCD2211010176、XCD2211010177、XCD2211010178、XCD2211010179、XCD2211010180、XCD2211010181、XCD2211010182、XCD2211010183、XCD2211010184、XCD2211010185、XCD2211010186、XCD2211010187、XCD2211010188、XCD2211010189、XCD2211010292、XCD2211010293、XCD2211010294、XCD2211010295、XCD2211010296、XCD2211010297、XCD2211010298、XCD2211010299、XCD2211010300、XCD2211010301、XCD2211010302、XCD2211010303、XCD2211010304、XCD2211010305、XCD2211010306、XCD2211010307、XCD2211010308、XCD2211010309、XCD2211010310、XCD2211010311、XCD2211010312、XCD2211010313、XCD2211010314、XCD2211010315、XCD2211010316、XCD2211010317、XCD2211010318、XCD2211010319、XCD2211010320、XCD2211010321、XCD2211010322、XCD2211010323、XCD2211010324、XCD2211010325、XCD2211010326、XCD2211010327、XCD2211010328、XCD2211010329、XCD2211010330、XCD2211010331、XCD2211010332、XCD2211010333、XCD2211010334、XCD2211010335、XCD2211010336、XCD2211010337、XCD2211010338、XCD2211010339、XCD2211010340、XCD2211010341、XCD2211010342、XCD2211010343、XCD2211010344、XCD2211010345、XCD2211010346、XCD2211010347、XCD2211010348、XCD2211010349、XCD2211010350、XCD2211010351、XCD2211010352 | Z25: 485996.63 | AA25: 10658978
A26: 4 | B26: 4500071502 | C26: 2022-09-29 | D26: 正泰新能科技有限公司 | E26: ①正面镀膜钢化玻璃_182双玻2272*1128*2.0mm（76500PC） ②背面网格钢化玻璃2272*1128*2.0（中间开3个12mm孔）短边无釉层（76500PC） | F26: ①2272*1128*2.0mm ②2272*1128*2.0 | G26: 153000 | H26: =I26/G26 | I26: 7876004 | J26: 2022-10-31 | K26: 待人工核对 | L26: 待人工核对 | M26: 待人工核对 | N26: 待人工核对 | O26: 待人工核对 | P26: 待人工核对 | X26: 2022-05-31 | Y26: XCD2206010002、XCD2206010009 | Z26: 410.05056 | AA26: 7653.79 | AB26: 待人工核对 | AC26: 待人工核对 | AD26: 待人工核对 | AE26: 系统结论：需人工复核；合同为多货物采购订单(PO)，货物名称/规格/数量已按行项目分条列示；G列数量=各行项目合计，H列单价=金额/数量(含税加权均价)；合同数量计量单位为「PC」，出库台账计量单位为「平方米」，口径不同，已分列不混填；物流记录(出库)已按出库日期逐行展开：一个日期一行，编号列汇总该日期全部出库单号，数量/金额为该日期合计；出库数量/金额为该客户全期出库台账合计，与单一PO金额口径不同，是否对应本合同批次需人工确认；发票/记账凭证/明细账不在本次材料范围（相应列留空）；勾稽：合同金额(7876003.95) 与出库金额合计(20682891.81) 不一致（口径不同，需人工判断是否合理）；签订日期(2022-09-29)晚于出库日期(2022-05-31)
X27: 2022-06-02 | Y27: XCD2206020002、XCD2206020003 | Z27: 410.05056 | AA27: 7653.79
X28: 2022-07-29 | Y28: XCD2207290017、XCD2207290020 | Z28: 282.4512 | AA28: 0
X29: 2022-09-30 | Y29: CKT2210020003、CKT2210020004、XCD2209300026、XCD2209300034、XCD2209300072、XCD2209300073、XCD2209300074、XCD2209300075、XCD2209300076、XCD2209300077、XCD2209300078、XCD2209300079、XCD2209300080、XCD2209300081、XCD2209300082、XCD2209300094、XCD2209300097、XCD2209300101、XCD2209300102、XCD2209300103、XCD2209300104、XCD2209300105、XCD2209300106、XCD2209300107、XCD2210010001、XCD2210010002、XCD2210010071、XCD2210010072、XCD2210010073、XCD2210010074、XCD2210010075、XCD2210010076、XCD2210010077、XCD2210010078、XCD2210010079、XCD2210010080、XCD2210010081、XCD2210010082、XCD2210010083、XCD2210010084、XCD2210010085、XCD2210010086、XCD2210010087、XCD2210010088、XCD2210010089、XCD2210010090、XCD2210010091、XCD2210010092、XCD2210010093、XCD2210010094 | Z29: 313688.68 | AA29: 5408249.2
X30: 2022-10-31 | Y30: CKT2211010003、CKT2211010004、CKT2211010005、CKT2211010006、CKT2211010007、CKT2211010008、CKT2211010009、CKT2211010010、CKT2211010011、CKT2211010012、CKT2211010018、XCD2211010039、XCD2211010040、XCD2211010042、XCD2211010043、XCD2211010044、XCD2211010046、XCD2211010047、XCD2211010048、XCD2211010049、XCD2211010050、XCD2211010051、XCD2211010077、XCD2211010079、XCD2211010080、XCD2211010081、XCD2211010082、XCD2211010083、XCD2211010084、XCD2211010085、XCD2211010086、XCD2211010087、XCD2211010088、XCD2211010089、XCD2211010090、XCD2211010091、XCD2211010093、XCD2211010094、XCD2211010095、XCD2211010096、XCD2211010097、XCD2211010098、XCD2211010099、XCD2211010100、XCD2211010101、XCD2211010102、XCD2211010103、XCD2211010104、XCD2211010105、XCD2211010106、XCD2211010107、XCD2211010108、XCD2211010109、XCD2211010110、XCD2211010111、XCD2211010112、XCD2211010113、XCD2211010114、XCD2211010115、XCD2211010116、XCD2211010117、XCD2211010119、XCD2211010121、XCD2211010190、XCD2211010191、XCD2211010192、XCD2211010193、XCD2211010194、XCD2211010195、XCD2211010203、XCD2211010204、XCD2211010205、XCD2211010206、XCD2211010207、XCD2211010208、XCD2211010214、XCD2211010218、XCD2211010223、XCD2211010224、XCD2211010225、XCD2211010226、XCD2211010227、XCD2211010228、XCD2211010229、XCD2211010232、XCD2211010353、XCD2211010354、XCD2211010355、XCD2211010356、XCD2211010357、XCD2211010358、XCD2211010359、XCD2211010360、XCD2211010361、XCD2211010362、XCD2211010363、XCD2211010364、XCD2211010365、XCD2211010366、XCD2211010367、XCD2211010368、XCD2211010369、XCD2211010370、XCD2211010371、XCD2211010372、XCD2211010373、XCD2211010374、XCD2211010375、XCD2211010376、XCD2211010377、XCD2211010378、XCD2211010379、XCD2211010380、XCD2211010381、XCD2211010382、XCD2211010383、XCD2211010384、XCD2211010385、XCD2211010386、XCD2211010387、XCD2211010388、XCD2211010389、XCD2211010390、XCD2211010391、XCD2211010392、XCD2211010393、XCD2211010394、XCD2211010395、XCD2211010396、XCD2211010397、XCD2211010398、XCD2211010399、XCD2211010400、XCD2211010401、XCD2211010402、XCD2211010403、XCD2211010404、XCD2211010405、XCD2211010406、XCD2211010407、XCD2211010408、XCD2211010409、XCD2211010410、XCD2211010411、XCD2211010412、XCD2211010413、XCD2211010414、XCD2211010415、XCD2211010416、XCD2211010417、XCD2211010418、XCD2211010419、XCD2211010420、XCD2211010421、XCD2211010422、XCD2211010423、XCD2211010424、XCD2211010425、XCD2211010426 | Z30: 854186.57 | AA30: 15259335
H43: =I43/G43
H44: =I44/G44
H45: =I45/G45
H46: =I46/G46
H47: =I47/G47

Sheet 主营业务收入细节测试（从明细账到合同）
A1: 主营业务收入细节测试记录表（从明细账到合同） | AH1: =HYPERLINK("#目录!A1","返回目录")
A2: =[1]目录!$A$2&[1]目录!$C$2 | L2: =[1]目录!$A$4&[1]目录!$C$4&" "&[1]目录!$A$5&[1]目录!$C$5 | AG2: ="索引号："&[1]目录!$D$53
A3: =[1]目录!$D$3&[1]目录!$F$3 | L3: =[1]目录!$D$4&[1]目录!$F$4&" "&[1]目录!$D$5&[1]目录!$F$5
A4: 入账情况 | H4: 检查内容 | V4: 其他支付性文件或说明 | W4: 检查内容 | AG4: 结论
H5: 销售合同、请购单内容 | N5: 销售发票 | R5: 物流记录或客户验收单 | W5: 常规检查 | AC5: 追加检查
A6: 序号 | B6: 日期 | C6: 凭证字 | D6: 凭证号 | E6: 凭证摘要 | F6: 对方科目 | G6: 入帐金额 | H6: 合同编号 | I6: 签约日期 | J6: 客户名称 | K6: 货名/规格/数量/单价 | L6: 金额 | M6: 约定交货时间 | N6: 日期 | O6: 编号 | P6: 数量 | Q6: 金额 | R6: 日期 | S6: 编号 | T6: 数量 | U6: 金额(如适用) | W6: ① | X6: ② | Y6: ③ | Z6: ④ | AA6: ⑤ | AB6: ⑥ | AC6: ⑦ | AD6: ⑧ | AE6: ⑨ | AF6: ⑩
